zeee_ai/__init__.py
zeee_ai/cli.py
zeee_ai-1.0.0.dist-info/licenses/LICENSE
zeee_ai-1.0.0.dist-info/METADATA
zeee_ai-1.0.0.dist-info/WHEEL
zeee_ai-1.0.0.dist-info/entry_points.txt
zeee_ai-1.0.0.dist-info/top_level.txt
zeee_ai-1.0.0.dist-info/RECORD
