Metadata-Version: 2.4
Name: zeee-ai
Version: 1.0.0
Summary: ZeeE AI: Zero Effort, Everything Enabled AI Assistant (CLI)
Home-page: https://github.com/AzizHorea/zeee-ai
Author: Muhammad Aziz ur Rehman
Author-email: azizhoreaofficial@gmail.com
Classifier: Programming Language :: Python :: 3
Classifier: Environment :: Console
Classifier: License :: OSI Approved :: MIT License
Classifier: Intended Audience :: Developers
Classifier: Operating System :: OS Independent
Classifier: Topic :: Utilities
Requires-Python: >=3.7
License-File: LICENSE
Requires-Dist: prompt_toolkit>=3.0.39
Requires-Dist: ollama>=0.1.0
Dynamic: author
Dynamic: author-email
Dynamic: classifier
Dynamic: description
Dynamic: description-content-type
Dynamic: home-page
Dynamic: license-file
Dynamic: requires-dist
Dynamic: requires-python
Dynamic: summary
